manyworlds/__init__.py
manyworlds/__main__.py
manyworlds/data_table.py
manyworlds/exceptions.py
manyworlds/feature.py
manyworlds/scenario.py
manyworlds/step.py
manyworlds-0.5.0.dist-info/METADATA
manyworlds-0.5.0.dist-info/WHEEL
manyworlds-0.5.0.dist-info/licenses/LICENSE
manyworlds-0.5.0.dist-info/RECORD
