Metadata-Version: 2.1
Name: manyworlds
Version: 0.5.0
Summary: Organize BDD scenarios as hierarchical trees for more concise and expressive feature files
Project-URL: Homepage, https://github.com/ingoweiss/manyworlds
Project-URL: Bug Tracker, https://github.com/ingoweiss/manyworlds/issues
Project-URL: Repository, https://github.com/ingoweiss/manyworlds.git
Project-URL: Changelog, https://github.com/ingoweiss/manyworlds/blob/master/CHANGELOG.md
Project-URL: Documentation, https://manyworlds.ingoweiss.com/
Author-email: Ingo Weiss <ingo@ingoweiss.com>
License: MIT License
License-File: LICENSE
Classifier: Development Status :: 3 - Alpha
Classifier: License :: OSI Approved :: MIT License
Classifier: Natural Language :: English
Classifier: Operating System :: OS Independent
Classifier: Programming Language :: Python :: 3
Classifier: Programming Language :: Python :: 3.8
Classifier: Programming Language :: Python :: 3.9
Classifier: Programming Language :: Python :: 3.10
Classifier: Programming Language :: Python :: 3.11
Classifier: Topic :: Software Development :: Quality Assurance
Classifier: Topic :: Software Development :: Testing
Classifier: Topic :: Software Development :: Testing :: BDD
Requires-Python: >=3.8
Requires-Dist: igraph
